README.md
setup.py
gen/python/asgt/data/v1/bq_entries_pb2.py
gen/python/asgt/data/v1/bq_entries_pb2_grpc.py
gen/python/asgt/data/v1/data_service_pb2.py
gen/python/asgt/data/v1/data_service_pb2_grpc.py
gen/python/asgt/jester/v1/jester_pb2.py
gen/python/asgt/jester/v1/jester_pb2_grpc.py
gen/python/asgt/modelregistry/v1/model_registry_pb2.py
gen/python/asgt/modelregistry/v1/model_registry_pb2_grpc.py
gen/python/asgt/type/data_pb2.py
gen/python/asgt/type/data_pb2_grpc.py
gen/python/asgt/type/dataset_pb2.py
gen/python/asgt/type/dataset_pb2_grpc.py
gen/python/asgt/type/model_pb2.py
gen/python/asgt/type/model_pb2_grpc.py
gen/python/asgt/type/prediction_pb2.py
gen/python/asgt/type/prediction_pb2_grpc.py
gen/python/asgt/type/retention_policy_pb2.py
gen/python/asgt/type/retention_policy_pb2_grpc.py
gen/python/asgt/type/revision_pb2.py
gen/python/asgt/type/revision_pb2_grpc.py
gen/python/asgt/type/sample_pb2.py
gen/python/asgt/type/sample_pb2_grpc.py
gen/python/asgt/type/target_metrics_pb2.py
gen/python/asgt/type/target_metrics_pb2_grpc.py
gen/python/asgt/type/target_value_pb2.py
gen/python/asgt/type/target_value_pb2_grpc.py
gen/python/asgt/type/train_model_task_pb2.py
gen/python/asgt/type/train_model_task_pb2_grpc.py
gen/python/gen_bq_schema/bq_field_pb2.py
gen/python/gen_bq_schema/bq_field_pb2_grpc.py
gen/python/gen_bq_schema/bq_table_pb2.py
gen/python/gen_bq_schema/bq_table_pb2_grpc.py
gen/python/ssn/__init__.py
gen/python/ssn/access/v1/access_pb2.py
gen/python/ssn/access/v1/access_pb2_grpc.py
gen/python/ssn/annotator/v1/annotator_pb2.py
gen/python/ssn/annotator/v1/annotator_pb2_grpc.py
gen/python/ssn/dataservice/v1/dataservice_pb2.py
gen/python/ssn/dataservice/v1/dataservice_pb2_grpc.py
gen/python/ssn/mlservice/v2/mlservice_pb2.py
gen/python/ssn/mlservice/v2/mlservice_pb2_grpc.py
gen/python/ssn/ocrservice/v1/ocrservice_pb2.py
gen/python/ssn/ocrservice/v1/ocrservice_pb2_grpc.py
gen/python/ssn/pdfservice/v1/pdfservice_pb2.py
vml_proto.egg-info/PKG-INFO
vml_proto.egg-info/SOURCES.txt
vml_proto.egg-info/dependency_links.txt
vml_proto.egg-info/not-zip-safe
vml_proto.egg-info/top_level.txt