Metadata-Version: 1.1
Name: vml-proto
Version: 0.0.0
Summary: A package containing vml protobuf definitions for python
Home-page: https://github.com/economic/vmlapis
Author: UNKNOWN
Author-email: UNKNOWN
License: UNKNOWN
Platform: UNKNOWN
Classifier: Programming Language :: Python :: 3
